info_gain/__init__.py
info_gain/info_gain.py
info_gain-1.0.1.dist-info/METADATA
info_gain-1.0.1.dist-info/RECORD
info_gain-1.0.1.dist-info/WHEEL
info_gain-1.0.1.dist-info/top_level.txt
