Metadata-Version: 2.1
Name: info-gain
Version: 1.0.1
Summary: Information gain utilities
Home-page: https://github.com/Thijsvanede/info_gain
Author: Thijs van Ede
Author-email: t.s.vanede@utwente.nl
License: UNKNOWN
Platform: UNKNOWN
Classifier: Programming Language :: Python :: 3
Classifier: License :: OSI Approved :: MIT License
Classifier: Operating System :: OS Independent
